README.md
setup.cfg
setup.py
pysolveengine/__init__.py
pysolveengine/basemodel.py
pysolveengine/client.py
pysolveengine/config.py
pysolveengine/converter_pb2.py
pysolveengine/converter_pb2_grpc.py
pysolveengine/helper.py
pysolveengine/mipmodel.py
pysolveengine/satmodel.py
pysolveengine/svc_jobs_pb2.py
pysolveengine/svc_jobs_pb2_grpc.py
pysolveengine/examples/__init__.py
pysolveengine/examples/usage_mip.py
pysolveengine/examples/usage_sat.py
test_pySolveEngine.egg-info/PKG-INFO
test_pySolveEngine.egg-info/SOURCES.txt
test_pySolveEngine.egg-info/dependency_links.txt
test_pySolveEngine.egg-info/requires.txt
test_pySolveEngine.egg-info/top_level.txt