Metadata-Version: 1.1
Name: test-pySolveEngine
Version: 0.3
Summary: A library to model MILP/SAT problems and have them solved via the SolveEngine using the web API
Home-page: https://github.com/alexandreMartinEcl/test_solveengine
Author: Karsten Lehmann
Author-email: karsten@satalia.com
License: UNKNOWN
Download-URL: https://github.com/alexandreMartinEcl/test_solveengine/archive/0.3.tar.gz
Keywords: SolveEngine MIP SAT Optimization
Platform: UNKNOWN
